rust_matchspec-0.2.1.dist-info/METADATA
rust_matchspec-0.2.1.dist-info/WHEEL
rust_matchspec-0.2.1.dist-info/license_files/LICENSE
rust_matchspec/__init__.py
rust_matchspec/rust_matchspec.pypy37-pp73-arm-linux-gnu.so
rust_matchspec-0.2.1.dist-info/RECORD
