Metadata-Version: 2.1
Name: rust_matchspec
Version: 0.2.1
Classifier: Programming Language :: Rust
Classifier: Programming Language :: Python :: Implementation :: CPython
Classifier: Programming Language :: Python :: Implementation :: PyPy
License-File: LICENSE
Summary: A conda matchspec written in Rust
Requires-Python: >=3.7
